callpass/__init__.py
callpass/__main__.py
callpass/callpass.py
callpass/exceptions.py
callpass/validated_callpass/__init__.py
callpass/validated_callpass/cache_heuristics.py
callpass/validated_callpass/license_validation_tools.py
callpass/validated_callpass/validated_callpass.py
callpass-0.4.0.dist-info/entry_points.txt
callpass-0.4.0.dist-info/LICENSE
callpass-0.4.0.dist-info/WHEEL
callpass-0.4.0.dist-info/METADATA
callpass-0.4.0.dist-info/RECORD
